weather_service/__init__.py
weather_service/server.py
weather_service-0.1.0.dist-info/METADATA
weather_service-0.1.0.dist-info/WHEEL
weather_service-0.1.0.dist-info/entry_points.txt
weather_service-0.1.0.dist-info/RECORD
