Metadata-Version: 2.4
Name: weather-service
Version: 0.1.0
Summary: A MCP server project
Requires-Python: >=3.12
Requires-Dist: httpx>=0.28.0
Requires-Dist: mcp>=1.0.0
Requires-Dist: python-dotenv>=1.0.1
